civitai_dl/__init__.py
civitai_dl/__main__.py
civitai_dl/api/__init__.py
civitai_dl/api/client.py
civitai_dl/cli/__init__.py
civitai_dl/cli/commands/browse.py
civitai_dl/cli/commands/config.py
civitai_dl/cli/commands/download.py
civitai_dl/cli/main.py
civitai_dl/config/proxy_settings.py
civitai_dl/core/__init__.py
civitai_dl/core/api.py
civitai_dl/core/config.py
civitai_dl/core/downloader.py
civitai_dl/core/file_utils.py
civitai_dl/core/filter.py
civitai_dl/utils/config.py
civitai_dl/utils/download.py
civitai_dl/utils/env.py
civitai_dl/utils/filter_test.py
civitai_dl/utils/formatter.py
civitai_dl/utils/logger.py
civitai_dl/utils/metadata.py
civitai_dl/utils/path_template.py
civitai_dl/webui/__init__.py
civitai_dl/webui/app.py
civitai_dl/webui/components/filter_builder.py
civitai_dl/webui/components/image_browser.py
civitai_dl/webui/components/model_search.py
civitai_dl/webui/pages/download_page.py
civitai_dl-0.1.2.dist-info/entry_points.txt
civitai_dl-0.1.2.dist-info/METADATA
civitai_dl-0.1.2.dist-info/WHEEL
civitai_dl-0.1.2.dist-info/RECORD
