Metadata-Version: 2.1
Name: civitai-dl
Version: 0.1.2
Summary: A tool for browsing and downloading resources from Civitai
Home-page: https://github.com/neverbiasu/civitai-dl
Keywords: civitai,ai,download,stable-diffusion
Author: Civitai Downloader Team
Requires-Python: >=3.8,<4.0
Classifier: Development Status :: 3 - Alpha
Classifier: Intended Audience :: End Users/Desktop
Classifier: License :: OSI Approved :: MIT License
Classifier: Programming Language :: Python :: 3
Classifier: Programming Language :: Python :: 3.8
Classifier: Programming Language :: Python :: 3.9
Classifier: Programming Language :: Python :: 3.10
Classifier: Programming Language :: Python :: 3.11
Classifier: Programming Language :: Python :: 3.12
Classifier: Programming Language :: Python :: 3.13
Classifier: Topic :: Multimedia :: Graphics
Requires-Dist: click (>=8.0.0,<9.0.0)
Requires-Dist: gradio (>=3.20.0,<4.0.0)
Requires-Dist: piexif (>=1.1.3,<2.0.0)
Requires-Dist: pillow (>=9.0.0,<10.0.0)
Requires-Dist: requests (>=2.28.0,<3.0.0)
Requires-Dist: tabulate (>=0.9.0,<0.10.0)
Requires-Dist: tqdm (>=4.64.0,<5.0.0)
Project-URL: Documentation, https://github.com/neverbiasu/civitai-dl
Project-URL: Repository, https://github.com/neverbiasu/civitai-dl
